tropir/__init__.py
tropir/rerun.py
tropir/session_utils.py
tropir-2.4.dist-info/METADATA
tropir-2.4.dist-info/WHEEL
tropir-2.4.dist-info/entry_points.txt
tropir-2.4.dist-info/top_level.txt
tropir-2.4.dist-info/RECORD
