Metadata-Version: 2.4
Name: tropir
Version: 2.4
Summary: A thin client for tracing LLM calls
Home-page: https://tropir.com
Author: Tropir
Author-email: founders@tropir.com
Classifier: Programming Language :: Python :: 3
Classifier: License :: OSI Approved :: MIT License
Classifier: Operating System :: OS Independent
Requires-Python: >=3.7
Dynamic: author
Dynamic: author-email
Dynamic: classifier
Dynamic: description
Dynamic: description-content-type
Dynamic: home-page
Dynamic: requires-python
Dynamic: summary
